[{"start": 0.0, "end": 16.95, "duration": 16.95}, {"start": 16.95, "end": 25.36, "duration": 8.41}, {"start": 25.36, "end": 39.46, "duration": 14.1}, {"start": 44.02, "end": 52.99, "duration": 8.97}, {"start": 52.99, "end": 57.02, "duration": 4.03}, {"start": 57.02, "end": 64.36, "duration": 7.34}, {"start": 64.36, "end": 67.1, "duration": 2.74}, {"start": 67.94, "end": 76.74, "duration": 8.8}, {"start": 76.74, "end": 87.63, "duration": 10.89}, {"start": 87.63, "end": 98.48, "duration": 10.85}, {"start": 98.48, "end": 112.39, "duration": 13.91}, {"start": 112.39, "end": 117.67, "duration": 5.28}, {"start": 118.56, "end": 128.51, "duration": 9.95}, {"start": 128.51, "end": 133.31, "duration": 4.8}, {"start": 133.31, "end": 141.46, "duration": 8.15}, {"start": 141.46, "end": 147.37, "duration": 5.91}, {"start": 147.37, "end": 154.47, "duration": 7.1}, {"start": 154.48, "end": 162.6, "duration": 8.12}, {"start": 162.6, "end": 170.64, "duration": 8.04}, {"start": 171.51, "end": 193.04, "duration": 21.53}, {"start": 193.04, "end": 199.05, "duration": 6.01}, {"start": 199.05, "end": 206.54, "duration": 7.49}, {"start": 206.54, "end": 218.49, "duration": 11.95}, {"start": 218.49, "end": 223.71, "duration": 5.22}, {"start": 224.82, "end": 234.78, "duration": 9.96}, {"start": 234.78, "end": 240.2, "duration": 5.42}, {"start": 240.2, "end": 252.12, "duration": 11.92}, {"start": 252.12, "end": 258.33, "duration": 6.21}, {"start": 258.33, "end": 263.15, "duration": 4.82}, {"start": 263.97, "end": 276.86, "duration": 12.89}, {"start": 276.86, "end": 284.19, "duration": 7.33}, {"start": 284.19, "end": 300.24, "duration": 16.05}, {"start": 300.24, "end": 313.66, "duration": 13.42}, {"start": 313.66, "end": 318.34, "duration": 4.68}, {"start": 318.34, "end": 326.81, "duration": 8.47}]