[{"start": 0.0, "end": 4.83, "duration": 4.83}, {"start": 4.83, "end": 38.23, "duration": 33.4}, {"start": 38.23, "end": 44.03, "duration": 5.8}, {"start": 44.03, "end": 56.57, "duration": 12.54}, {"start": 56.57, "end": 86.05, "duration": 29.48}, {"start": 86.05, "end": 89.27, "duration": 3.22}, {"start": 89.27, "end": 95.42, "duration": 6.15}, {"start": 95.42, "end": 104.01, "duration": 8.59}, {"start": 104.01, "end": 121.94, "duration": 17.93}, {"start": 121.94, "end": 124.61, "duration": 2.67}, {"start": 124.61, "end": 150.64, "duration": 26.03}, {"start": 151.2, "end": 200.9, "duration": 49.7}, {"start": 200.9, "end": 213.41, "duration": 12.51}, {"start": 213.41, "end": 236.72, "duration": 23.31}, {"start": 236.72, "end": 283.63, "duration": 46.91}, {"start": 283.63, "end": 297.9, "duration": 14.27}, {"start": 297.9, "end": 406.8, "duration": 108.9}, {"start": 406.8, "end": 428.76, "duration": 21.96}, {"start": 428.76, "end": 450.2, "duration": 21.44}, {"start": 450.2, "end": 493.59, "duration": 43.39}, {"start": 493.59, "end": 536.63, "duration": 43.04}, {"start": 536.63, "end": 574.94, "duration": 38.31}, {"start": 574.94, "end": 583.41, "duration": 8.47}]