[{"start": 0.0, "end": 7.14, "duration": 7.14}, {"start": 7.14, "end": 23.18, "duration": 16.04}, {"start": 23.18, "end": 54.52, "duration": 31.34}, {"start": 54.52, "end": 62.37, "duration": 7.85}, {"start": 62.37, "end": 70.15, "duration": 7.78}, {"start": 70.15, "end": 96.67, "duration": 26.52}, {"start": 96.67, "end": 103.14, "duration": 6.47}, {"start": 103.14, "end": 112.21, "duration": 9.07}, {"start": 112.21, "end": 146.91, "duration": 34.7}, {"start": 146.91, "end": 153.45, "duration": 6.54}, {"start": 153.45, "end": 159.46, "duration": 6.01}, {"start": 159.46, "end": 165.56, "duration": 6.1}, {"start": 165.56, "end": 183.73, "duration": 18.17}, {"start": 183.73, "end": 196.76, "duration": 13.03}, {"start": 196.76, "end": 205.35, "duration": 8.59}, {"start": 205.35, "end": 210.39, "duration": 5.04}, {"start": 210.39, "end": 238.9, "duration": 28.51}, {"start": 238.9, "end": 247.65, "duration": 8.75}, {"start": 247.65, "end": 251.07, "duration": 3.42}, {"start": 251.07, "end": 255.66, "duration": 4.59}, {"start": 255.66, "end": 273.56, "duration": 17.9}, {"start": 273.56, "end": 282.36, "duration": 8.8}, {"start": 282.36, "end": 316.43, "duration": 34.07}, {"start": 316.43, "end": 325.54, "duration": 9.11}, {"start": 325.54, "end": 332.93, "duration": 7.39}, {"start": 332.93, "end": 351.29, "duration": 18.36}, {"start": 351.29, "end": 365.5, "duration": 14.21}, {"start": 365.5, "end": 389.75, "duration": 24.25}, {"start": 389.75, "end": 393.59, "duration": 3.84}, {"start": 393.59, "end": 409.27, "duration": 15.68}, {"start": 409.27, "end": 437.31, "duration": 28.04}, {"start": 437.31, "end": 450.29, "duration": 12.98}, {"start": 450.29, "end": 454.36, "duration": 4.07}, {"start": 454.36, "end": 466.1, "duration": 11.74}, {"start": 466.1, "end": 471.64, "duration": 5.54}, {"start": 471.64, "end": 479.7, "duration": 8.06}, {"start": 479.7, "end": 490.37, "duration": 10.67}, {"start": 490.37, "end": 513.08, "duration": 22.71}, {"start": 513.08, "end": 517.38, "duration": 4.3}, {"start": 517.38, "end": 525.21, "duration": 7.83}, {"start": 525.21, "end": 528.36, "duration": 3.15}, {"start": 528.43, "end": 531.78, "duration": 3.35}, {"start": 531.78, "end": 534.46, "duration": 2.68}, {"start": 534.46, "end": 548.52, "duration": 14.06}, {"start": 548.52, "end": 551.96, "duration": 3.44}, {"start": 551.96, "end": 559.23, "duration": 7.27}, {"start": 559.23, "end": 565.43, "duration": 6.2}, {"start": 565.43, "end": 568.39, "duration": 2.96}, {"start": 568.39, "end": 573.09, "duration": 4.7}, {"start": 573.09, "end": 579.49, "duration": 6.4}, {"start": 579.49, "end": 582.24, "duration": 2.75}, {"start": 582.24, "end": 587.1, "duration": 4.86}, {"start": 587.1, "end": 592.41, "duration": 5.31}, {"start": 592.41, "end": 608.71, "duration": 16.3}, {"start": 608.71, "end": 625.94, "duration": 17.23}, {"start": 625.94, "end": 631.37, "duration": 5.43}, {"start": 631.41, "end": 655.1, "duration": 23.69}, {"start": 655.1, "end": 661.55, "duration": 6.45}]