[{"start": 0.26, "end": 6.58, "duration": 6.32}, {"start": 6.58, "end": 9.25, "duration": 2.67}, {"start": 9.25, "end": 12.07, "duration": 2.82}, {"start": 12.12, "end": 15.51, "duration": 3.39}, {"start": 15.51, "end": 23.5, "duration": 7.99}, {"start": 23.5, "end": 28.0, "duration": 4.5}, {"start": 28.0, "end": 31.44, "duration": 3.44}, {"start": 31.44, "end": 34.31, "duration": 2.87}, {"start": 36.57, "end": 41.74, "duration": 5.17}, {"start": 41.74, "end": 44.41, "duration": 2.67}, {"start": 44.41, "end": 47.85, "duration": 3.44}, {"start": 47.9, "end": 52.62, "duration": 4.72}, {"start": 52.62, "end": 55.85, "duration": 3.23}, {"start": 55.85, "end": 59.64, "duration": 3.79}, {"start": 59.64, "end": 63.52, "duration": 3.88}, {"start": 63.52, "end": 67.23, "duration": 3.71}, {"start": 67.23, "end": 72.68, "duration": 5.45}, {"start": 72.68, "end": 76.57, "duration": 3.89}, {"start": 76.57, "end": 79.47, "duration": 2.9}, {"start": 79.47, "end": 82.99, "duration": 3.52}, {"start": 82.99, "end": 85.67, "duration": 2.68}, {"start": 85.67, "end": 89.02, "duration": 3.35}, {"start": 89.02, "end": 92.19, "duration": 3.17}, {"start": 92.19, "end": 96.26, "duration": 4.07}, {"start": 96.26, "end": 100.2, "duration": 3.94}, {"start": 100.2, "end": 103.73, "duration": 3.53}, {"start": 106.08, "end": 110.24, "duration": 4.16}, {"start": 110.24, "end": 113.12, "duration": 2.88}, {"start": 113.12, "end": 115.97, "duration": 2.85}, {"start": 115.97, "end": 118.82, "duration": 2.85}, {"start": 118.82, "end": 121.83, "duration": 3.01}, {"start": 121.83, "end": 125.42, "duration": 3.59}, {"start": 125.42, "end": 129.15, "duration": 3.73}, {"start": 129.15, "end": 131.71, "duration": 2.56}, {"start": 131.71, "end": 135.09, "duration": 3.38}, {"start": 135.09, "end": 138.03, "duration": 2.94}, {"start": 138.03, "end": 140.81, "duration": 2.78}, {"start": 140.81, "end": 144.7, "duration": 3.89}, {"start": 144.7, "end": 147.28, "duration": 2.58}, {"start": 147.28, "end": 151.06, "duration": 3.78}, {"start": 151.06, "end": 153.6, "duration": 2.54}, {"start": 153.6, "end": 157.34, "duration": 3.74}, {"start": 157.34, "end": 161.32, "duration": 3.98}, {"start": 161.32, "end": 164.86, "duration": 3.54}, {"start": 164.86, "end": 168.91, "duration": 4.05}, {"start": 168.91, "end": 172.27, "duration": 3.36}, {"start": 172.27, "end": 176.09, "duration": 3.82}, {"start": 176.09, "end": 180.1, "duration": 4.01}, {"start": 180.1, "end": 183.26, "duration": 3.16}, {"start": 183.26, "end": 186.49, "duration": 3.23}, {"start": 188.49, "end": 191.28, "duration": 2.79}, {"start": 191.28, "end": 193.97, "duration": 2.69}, {"start": 194.0, "end": 197.24, "duration": 3.24}, {"start": 197.24, "end": 200.76, "duration": 3.52}, {"start": 200.79, "end": 205.47, "duration": 4.68}, {"start": 207.94, "end": 212.3, "duration": 4.36}, {"start": 212.33, "end": 216.44, "duration": 4.11}, {"start": 216.44, "end": 220.21, "duration": 3.77}, {"start": 220.21, "end": 224.89, "duration": 4.68}, {"start": 224.89, "end": 228.82, "duration": 3.93}, {"start": 228.82, "end": 232.41, "duration": 3.59}, {"start": 234.83, "end": 237.56, "duration": 2.73}, {"start": 237.56, "end": 241.24, "duration": 3.68}, {"start": 241.24, "end": 245.59, "duration": 4.35}, {"start": 245.59, "end": 249.69, "duration": 4.1}, {"start": 249.69, "end": 253.61, "duration": 3.92}, {"start": 253.61, "end": 257.08, "duration": 3.47}, {"start": 257.11, "end": 261.27, "duration": 4.16}, {"start": 261.27, "end": 264.97, "duration": 3.7}, {"start": 264.97, "end": 268.59, "duration": 3.62}, {"start": 268.59, "end": 272.32, "duration": 3.73}, {"start": 272.32, "end": 275.62, "duration": 3.3}, {"start": 275.62, "end": 278.71, "duration": 3.09}, {"start": 281.25, "end": 285.07, "duration": 3.82}, {"start": 287.33, "end": 290.75, "duration": 3.42}, {"start": 290.75, "end": 293.82, "duration": 3.07}, {"start": 293.82, "end": 298.12, "duration": 4.3}, {"start": 302.93, "end": 305.94, "duration": 3.01}, {"start": 305.94, "end": 308.61, "duration": 2.67}, {"start": 310.87, "end": 314.52, "duration": 3.65}, {"start": 314.52, "end": 318.31, "duration": 3.79}, {"start": 318.31, "end": 321.01, "duration": 2.7}, {"start": 321.01, "end": 324.56, "duration": 3.55}, {"start": 324.69, "end": 328.69, "duration": 4.0}, {"start": 328.69, "end": 331.57, "duration": 2.88}, {"start": 333.95, "end": 336.57, "duration": 2.62}, {"start": 336.57, "end": 340.74, "duration": 4.17}, {"start": 343.22, "end": 347.51, "duration": 4.29}, {"start": 347.51, "end": 351.2, "duration": 3.69}, {"start": 353.65, "end": 356.79, "duration": 3.14}, {"start": 356.79, "end": 359.49, "duration": 2.7}, {"start": 359.49, "end": 363.11, "duration": 3.62}, {"start": 363.11, "end": 366.84, "duration": 3.73}, {"start": 366.84, "end": 369.52, "duration": 2.68}, {"start": 369.52, "end": 372.06, "duration": 2.54}, {"start": 372.06, "end": 375.44, "duration": 3.38}, {"start": 375.44, "end": 379.62, "duration": 4.18}, {"start": 381.98, "end": 385.39, "duration": 3.41}, {"start": 387.86, "end": 390.65, "duration": 2.79}, {"start": 392.72, "end": 395.49, "duration": 2.77}, {"start": 395.49, "end": 398.4, "duration": 2.91}, {"start": 398.4, "end": 401.1, "duration": 2.7}, {"start": 401.19, "end": 404.98, "duration": 3.79}, {"start": 404.98, "end": 408.01, "duration": 3.03}, {"start": 408.01, "end": 412.96, "duration": 4.95}, {"start": 412.96, "end": 415.77, "duration": 2.81}, {"start": 415.77, "end": 418.7, "duration": 2.93}, {"start": 418.7, "end": 422.2, "duration": 3.5}, {"start": 424.32, "end": 428.21, "duration": 3.89}, {"start": 428.21, "end": 432.75, "duration": 4.54}, {"start": 432.75, "end": 436.99, "duration": 4.24}, {"start": 439.16, "end": 442.18, "duration": 3.02}, {"start": 446.64, "end": 449.57, "duration": 2.93}, {"start": 449.61, "end": 453.11, "duration": 3.5}, {"start": 455.57, "end": 458.67, "duration": 3.1}, {"start": 463.02, "end": 466.92, "duration": 3.9}, {"start": 466.92, "end": 470.64, "duration": 3.72}, {"start": 470.64, "end": 473.45, "duration": 2.81}, {"start": 473.45, "end": 478.55, "duration": 5.1}, {"start": 478.55, "end": 482.21, "duration": 3.66}, {"start": 486.88, "end": 490.04, "duration": 3.16}, {"start": 490.04, "end": 493.7, "duration": 3.66}, {"start": 493.7, "end": 496.28, "duration": 2.58}, {"start": 496.28, "end": 499.94, "duration": 3.66}, {"start": 499.94, "end": 502.82, "duration": 2.88}, {"start": 502.82, "end": 507.49, "duration": 4.67}, {"start": 507.49, "end": 510.48, "duration": 2.99}, {"start": 510.48, "end": 513.14, "duration": 2.66}, {"start": 513.14, "end": 517.17, "duration": 4.03}, {"start": 519.63, "end": 522.66, "duration": 3.03}, {"start": 522.66, "end": 526.36, "duration": 3.7}, {"start": 526.36, "end": 531.47, "duration": 5.11}, {"start": 531.47, "end": 534.94, "duration": 3.47}, {"start": 534.94, "end": 539.42, "duration": 4.48}, {"start": 539.42, "end": 544.16, "duration": 4.74}, {"start": 544.16, "end": 547.57, "duration": 3.41}, {"start": 547.57, "end": 550.59, "duration": 3.02}, {"start": 550.59, "end": 554.02, "duration": 3.43}, {"start": 554.02, "end": 557.68, "duration": 3.66}, {"start": 558.0, "end": 561.04, "duration": 3.04}, {"start": 563.48, "end": 566.08, "duration": 2.6}, {"start": 566.08, "end": 568.79, "duration": 2.71}, {"start": 568.79, "end": 572.21, "duration": 3.42}, {"start": 572.21, "end": 576.81, "duration": 4.6}, {"start": 576.81, "end": 579.94, "duration": 3.13}, {"start": 579.94, "end": 583.44, "duration": 3.5}, {"start": 583.44, "end": 586.22, "duration": 2.78}, {"start": 586.22, "end": 590.08, "duration": 3.86}, {"start": 590.08, "end": 593.05, "duration": 2.97}, {"start": 593.05, "end": 596.48, "duration": 3.43}, {"start": 596.48, "end": 599.73, "duration": 3.25}, {"start": 599.73, "end": 603.13, "duration": 3.4}, {"start": 603.13, "end": 607.83, "duration": 4.7}, {"start": 607.83, "end": 611.44, "duration": 3.61}, {"start": 611.44, "end": 614.23, "duration": 2.79}, {"start": 614.23, "end": 618.23, "duration": 4.0}, {"start": 618.23, "end": 621.14, "duration": 2.91}, {"start": 621.14, "end": 624.81, "duration": 3.67}, {"start": 624.86, "end": 629.36, "duration": 4.5}, {"start": 629.36, "end": 631.96, "duration": 2.6}, {"start": 631.96, "end": 635.48, "duration": 3.52}, {"start": 635.48, "end": 639.14, "duration": 3.66}, {"start": 641.49, "end": 645.24, "duration": 3.75}, {"start": 645.24, "end": 647.76, "duration": 2.52}, {"start": 647.76, "end": 650.91, "duration": 3.15}, {"start": 650.91, "end": 655.28, "duration": 4.37}, {"start": 657.41, "end": 660.11, "duration": 2.7}, {"start": 660.11, "end": 663.77, "duration": 3.66}, {"start": 665.99, "end": 669.01, "duration": 3.02}, {"start": 669.01, "end": 672.64, "duration": 3.63}, {"start": 672.64, "end": 676.82, "duration": 4.18}, {"start": 676.82, "end": 681.55, "duration": 4.73}, {"start": 683.71, "end": 687.58, "duration": 3.87}, {"start": 687.63, "end": 690.64, "duration": 3.01}, {"start": 690.64, "end": 693.4, "duration": 2.76}, {"start": 693.4, "end": 696.22, "duration": 2.82}, {"start": 698.47, "end": 701.87, "duration": 3.4}, {"start": 701.87, "end": 705.52, "duration": 3.65}, {"start": 705.52, "end": 708.7, "duration": 3.18}, {"start": 708.7, "end": 711.3, "duration": 2.6}, {"start": 711.3, "end": 714.7, "duration": 3.4}, {"start": 714.7, "end": 717.34, "duration": 2.64}, {"start": 717.35, "end": 721.54, "duration": 4.19}, {"start": 721.54, "end": 724.54, "duration": 3.0}, {"start": 724.54, "end": 728.98, "duration": 4.44}, {"start": 728.98, "end": 733.45, "duration": 4.47}, {"start": 733.45, "end": 736.65, "duration": 3.2}, {"start": 736.65, "end": 739.55, "duration": 2.9}, {"start": 741.93, "end": 745.04, "duration": 3.11}, {"start": 747.51, "end": 752.06, "duration": 4.55}, {"start": 752.06, "end": 757.76, "duration": 5.7}, {"start": 757.76, "end": 760.41, "duration": 2.65}, {"start": 760.41, "end": 763.41, "duration": 3.0}, {"start": 763.41, "end": 766.5, "duration": 3.09}, {"start": 766.5, "end": 769.57, "duration": 3.07}, {"start": 769.64, "end": 773.05, "duration": 3.41}, {"start": 773.05, "end": 776.36, "duration": 3.31}, {"start": 776.36, "end": 779.98, "duration": 3.62}, {"start": 779.98, "end": 783.89, "duration": 3.91}, {"start": 783.89, "end": 788.28, "duration": 4.39}, {"start": 788.28, "end": 792.39, "duration": 4.11}, {"start": 792.39, "end": 796.85, "duration": 4.46}, {"start": 799.19, "end": 802.61, "duration": 3.42}, {"start": 802.61, "end": 806.23, "duration": 3.62}, {"start": 806.23, "end": 808.89, "duration": 2.66}, {"start": 808.89, "end": 811.99, "duration": 3.1}, {"start": 811.99, "end": 815.54, "duration": 3.55}, {"start": 815.54, "end": 818.4, "duration": 2.86}, {"start": 818.4, "end": 823.49, "duration": 5.09}, {"start": 823.49, "end": 826.89, "duration": 3.4}, {"start": 829.36, "end": 833.93, "duration": 4.57}, {"start": 833.93, "end": 837.73, "duration": 3.8}, {"start": 837.73, "end": 841.69, "duration": 3.96}, {"start": 841.69, "end": 845.56, "duration": 3.87}, {"start": 845.56, "end": 848.18, "duration": 2.62}, {"start": 850.57, "end": 853.2, "duration": 2.63}, {"start": 853.2, "end": 856.61, "duration": 3.41}, {"start": 856.61, "end": 860.18, "duration": 3.57}, {"start": 860.18, "end": 863.84, "duration": 3.66}, {"start": 863.84, "end": 866.78, "duration": 2.94}, {"start": 866.78, "end": 870.79, "duration": 4.01}, {"start": 870.79, "end": 874.75, "duration": 3.96}, {"start": 874.75, "end": 879.76, "duration": 5.01}, {"start": 879.76, "end": 882.6, "duration": 2.84}, {"start": 882.6, "end": 886.47, "duration": 3.87}, {"start": 886.53, "end": 890.6, "duration": 4.07}, {"start": 890.6, "end": 893.3, "duration": 2.7}, {"start": 893.3, "end": 896.81, "duration": 3.51}, {"start": 896.81, "end": 901.63, "duration": 4.82}, {"start": 901.63, "end": 904.35, "duration": 2.72}, {"start": 904.35, "end": 908.89, "duration": 4.54}, {"start": 908.89, "end": 912.5, "duration": 3.61}, {"start": 912.5, "end": 916.64, "duration": 4.14}, {"start": 916.64, "end": 920.51, "duration": 3.87}, {"start": 920.51, "end": 923.95, "duration": 3.44}, {"start": 926.29, "end": 929.38, "duration": 3.09}, {"start": 929.38, "end": 932.7, "duration": 3.32}, {"start": 932.7, "end": 935.93, "duration": 3.23}, {"start": 935.93, "end": 939.62, "duration": 3.69}, {"start": 943.94, "end": 947.35, "duration": 3.41}, {"start": 947.35, "end": 951.9, "duration": 4.55}, {"start": 951.9, "end": 955.14, "duration": 3.24}, {"start": 955.14, "end": 960.01, "duration": 4.87}, {"start": 960.01, "end": 963.26, "duration": 3.25}, {"start": 963.26, "end": 966.13, "duration": 2.87}, {"start": 966.13, "end": 968.87, "duration": 2.74}, {"start": 968.87, "end": 972.62, "duration": 3.75}, {"start": 972.62, "end": 975.66, "duration": 3.04}, {"start": 975.66, "end": 979.83, "duration": 4.17}, {"start": 979.83, "end": 983.4, "duration": 3.57}, {"start": 985.53, "end": 988.28, "duration": 2.75}, {"start": 988.28, "end": 991.05, "duration": 2.77}, {"start": 991.05, "end": 994.05, "duration": 3.0}, {"start": 994.05, "end": 997.14, "duration": 3.09}, {"start": 997.14, "end": 1000.98, "duration": 3.84}, {"start": 1003.47, "end": 1006.08, "duration": 2.61}, {"start": 1008.36, "end": 1011.42, "duration": 3.06}, {"start": 1011.42, "end": 1014.49, "duration": 3.07}, {"start": 1016.74, "end": 1019.77, "duration": 3.03}, {"start": 1019.77, "end": 1023.64, "duration": 3.87}, {"start": 1023.64, "end": 1027.1, "duration": 3.46}, {"start": 1027.1, "end": 1030.21, "duration": 3.11}, {"start": 1030.21, "end": 1033.86, "duration": 3.65}, {"start": 1033.86, "end": 1036.81, "duration": 2.95}, {"start": 1036.81, "end": 1040.49, "duration": 3.68}, {"start": 1040.49, "end": 1043.25, "duration": 2.76}, {"start": 1043.25, "end": 1046.06, "duration": 2.81}, {"start": 1050.68, "end": 1054.63, "duration": 3.95}, {"start": 1054.63, "end": 1057.56, "duration": 2.93}, {"start": 1057.6, "end": 1062.05, "duration": 4.45}, {"start": 1062.05, "end": 1065.0, "duration": 2.95}, {"start": 1065.0, "end": 1068.62, "duration": 3.62}, {"start": 1068.62, "end": 1071.94, "duration": 3.32}, {"start": 1071.94, "end": 1075.25, "duration": 3.31}, {"start": 1075.25, "end": 1079.27, "duration": 4.02}, {"start": 1079.27, "end": 1082.26, "duration": 2.99}, {"start": 1082.26, "end": 1085.13, "duration": 2.87}, {"start": 1085.13, "end": 1088.34, "duration": 3.21}, {"start": 1088.34, "end": 1091.96, "duration": 3.62}, {"start": 1091.96, "end": 1094.53, "duration": 2.57}, {"start": 1094.53, "end": 1097.03, "duration": 2.5}, {"start": 1097.03, "end": 1100.39, "duration": 3.36}, {"start": 1100.39, "end": 1103.39, "duration": 3.0}, {"start": 1105.88, "end": 1110.38, "duration": 4.5}, {"start": 1110.38, "end": 1113.64, "duration": 3.26}, {"start": 1113.64, "end": 1116.78, "duration": 3.14}, {"start": 1116.78, "end": 1120.24, "duration": 3.46}, {"start": 1120.24, "end": 1123.33, "duration": 3.09}, {"start": 1123.33, "end": 1126.17, "duration": 2.84}, {"start": 1128.54, "end": 1131.68, "duration": 3.14}, {"start": 1131.68, "end": 1135.24, "duration": 3.56}, {"start": 1135.24, "end": 1139.25, "duration": 4.01}, {"start": 1139.25, "end": 1142.18, "duration": 2.93}, {"start": 1142.18, "end": 1145.92, "duration": 3.74}, {"start": 1145.92, "end": 1148.69, "duration": 2.77}, {"start": 1148.69, "end": 1151.87, "duration": 3.18}, {"start": 1151.87, "end": 1155.01, "duration": 3.14}, {"start": 1155.01, "end": 1158.55, "duration": 3.54}, {"start": 1158.55, "end": 1161.7, "duration": 3.15}, {"start": 1161.7, "end": 1164.88, "duration": 3.18}, {"start": 1164.88, "end": 1167.77, "duration": 2.89}, {"start": 1167.77, "end": 1170.52, "duration": 2.75}, {"start": 1170.56, "end": 1173.66, "duration": 3.1}, {"start": 1173.66, "end": 1176.56, "duration": 2.9}, {"start": 1176.56, "end": 1179.61, "duration": 3.05}, {"start": 1179.61, "end": 1182.81, "duration": 3.2}, {"start": 1182.81, "end": 1185.42, "duration": 2.61}, {"start": 1185.42, "end": 1189.47, "duration": 4.05}, {"start": 1189.47, "end": 1192.73, "duration": 3.26}, {"start": 1192.73, "end": 1196.08, "duration": 3.35}, {"start": 1196.08, "end": 1199.75, "duration": 3.67}, {"start": 1202.12, "end": 1205.63, "duration": 3.51}, {"start": 1207.99, "end": 1210.67, "duration": 2.68}, {"start": 1213.07, "end": 1216.86, "duration": 3.79}, {"start": 1219.34, "end": 1222.99, "duration": 3.65}, {"start": 1222.99, "end": 1225.6, "duration": 2.61}, {"start": 1225.6, "end": 1229.09, "duration": 3.49}, {"start": 1229.09, "end": 1231.76, "duration": 2.67}, {"start": 1231.76, "end": 1234.8, "duration": 3.04}, {"start": 1234.8, "end": 1237.47, "duration": 2.67}, {"start": 1237.47, "end": 1240.59, "duration": 3.12}, {"start": 1240.59, "end": 1244.04, "duration": 3.45}, {"start": 1244.04, "end": 1247.55, "duration": 3.51}, {"start": 1247.68, "end": 1250.82, "duration": 3.14}, {"start": 1250.82, "end": 1253.65, "duration": 2.83}, {"start": 1256.09, "end": 1258.93, "duration": 2.84}, {"start": 1258.93, "end": 1261.59, "duration": 2.66}, {"start": 1261.59, "end": 1264.39, "duration": 2.8}, {"start": 1264.39, "end": 1268.89, "duration": 4.5}, {"start": 1268.89, "end": 1271.65, "duration": 2.76}, {"start": 1276.37, "end": 1279.47, "duration": 3.1}, {"start": 1279.47, "end": 1282.48, "duration": 3.01}, {"start": 1282.48, "end": 1286.66, "duration": 4.18}, {"start": 1286.66, "end": 1289.35, "duration": 2.69}]