[{"start": 0.0, "end": 5.47, "duration": 5.47}, {"start": 5.47, "end": 52.66, "duration": 47.19}, {"start": 52.66, "end": 95.63, "duration": 42.97}, {"start": 95.63, "end": 128.79, "duration": 33.16}, {"start": 128.79, "end": 145.14, "duration": 16.35}, {"start": 145.6, "end": 336.6, "duration": 191.0}, {"start": 336.6, "end": 404.49, "duration": 67.89}, {"start": 404.49, "end": 420.09, "duration": 15.6}, {"start": 420.09, "end": 474.45, "duration": 54.36}, {"start": 475.0, "end": 531.07, "duration": 56.07}, {"start": 531.07, "end": 535.61, "duration": 4.54}, {"start": 535.61, "end": 546.98, "duration": 11.37}, {"start": 546.98, "end": 572.0, "duration": 25.02}, {"start": 572.0, "end": 593.58, "duration": 21.58}]