[{"start": 0.0, "end": 6.48, "duration": 6.48}, {"start": 6.48, "end": 15.85, "duration": 9.37}, {"start": 15.85, "end": 29.94, "duration": 14.09}, {"start": 30.18, "end": 39.61, "duration": 9.43}, {"start": 39.61, "end": 51.14, "duration": 11.53}, {"start": 53.65, "end": 64.44, "duration": 10.79}, {"start": 64.44, "end": 78.2, "duration": 13.76}, {"start": 78.2, "end": 84.81, "duration": 6.61}, {"start": 84.81, "end": 104.84, "duration": 20.03}, {"start": 104.84, "end": 108.48, "duration": 3.64}, {"start": 108.48, "end": 130.13, "duration": 21.65}, {"start": 130.59, "end": 136.7, "duration": 6.11}, {"start": 136.7, "end": 139.61, "duration": 2.91}, {"start": 139.61, "end": 148.51, "duration": 8.9}, {"start": 148.51, "end": 154.62, "duration": 6.11}, {"start": 154.62, "end": 159.32, "duration": 4.7}, {"start": 159.32, "end": 164.13, "duration": 4.81}, {"start": 164.13, "end": 174.12, "duration": 9.99}]