[{"start": 2.68, "end": 9.57, "duration": 6.89}, {"start": 10.42, "end": 48.19, "duration": 37.77}, {"start": 50.75, "end": 80.08, "duration": 29.33}, {"start": 81.45, "end": 84.19, "duration": 2.74}, {"start": 86.91, "end": 103.98, "duration": 17.07}, {"start": 104.97, "end": 110.5, "duration": 5.53}, {"start": 110.5, "end": 123.14, "duration": 12.64}, {"start": 124.23, "end": 131.69, "duration": 7.46}, {"start": 132.66, "end": 158.62, "duration": 25.96}, {"start": 158.62, "end": 169.87, "duration": 11.25}, {"start": 171.2, "end": 179.93, "duration": 8.73}, {"start": 179.93, "end": 201.9, "duration": 21.97}, {"start": 201.9, "end": 206.15, "duration": 4.25}, {"start": 206.15, "end": 228.48, "duration": 22.33}, {"start": 228.48, "end": 237.94, "duration": 9.46}, {"start": 237.94, "end": 251.37, "duration": 13.43}, {"start": 251.37, "end": 255.77, "duration": 4.4}, {"start": 255.77, "end": 262.74, "duration": 6.97}, {"start": 265.63, "end": 268.94, "duration": 3.31}, {"start": 269.02, "end": 282.7, "duration": 13.68}, {"start": 282.7, "end": 290.0, "duration": 7.3}, {"start": 290.0, "end": 292.75, "duration": 2.75}, {"start": 292.75, "end": 303.86, "duration": 11.11}, {"start": 303.86, "end": 310.68, "duration": 6.82}, {"start": 310.68, "end": 323.08, "duration": 12.4}, {"start": 323.08, "end": 333.97, "duration": 10.89}, {"start": 333.97, "end": 340.57, "duration": 6.6}, {"start": 341.23, "end": 345.54, "duration": 4.31}, {"start": 345.54, "end": 350.08, "duration": 4.54}, {"start": 350.08, "end": 359.72, "duration": 9.64}]