[{"start": 0.33, "end": 5.63, "duration": 5.3}, {"start": 5.63, "end": 12.0, "duration": 6.37}, {"start": 12.0, "end": 18.4, "duration": 6.4}, {"start": 18.4, "end": 29.3, "duration": 10.9}, {"start": 29.3, "end": 40.72, "duration": 11.42}, {"start": 40.72, "end": 51.42, "duration": 10.7}, {"start": 51.42, "end": 54.52, "duration": 3.1}, {"start": 54.52, "end": 91.2, "duration": 36.68}, {"start": 91.2, "end": 97.17, "duration": 5.97}, {"start": 97.17, "end": 103.55, "duration": 6.38}, {"start": 103.55, "end": 114.92, "duration": 11.37}, {"start": 114.92, "end": 124.12, "duration": 9.2}, {"start": 124.12, "end": 128.2, "duration": 4.08}, {"start": 128.2, "end": 151.12, "duration": 22.92}, {"start": 151.12, "end": 153.85, "duration": 2.73}, {"start": 153.85, "end": 157.62, "duration": 3.77}, {"start": 157.62, "end": 163.3, "duration": 5.68}, {"start": 163.3, "end": 168.96, "duration": 5.66}, {"start": 168.96, "end": 175.67, "duration": 6.71}, {"start": 175.67, "end": 181.08, "duration": 5.41}, {"start": 181.08, "end": 187.51, "duration": 6.43}, {"start": 187.51, "end": 195.77, "duration": 8.26}, {"start": 195.77, "end": 211.59, "duration": 15.82}, {"start": 211.59, "end": 233.31, "duration": 21.72}, {"start": 233.31, "end": 241.34, "duration": 8.03}, {"start": 243.79, "end": 248.52, "duration": 4.73}, {"start": 248.52, "end": 286.56, "duration": 38.04}, {"start": 286.56, "end": 290.63, "duration": 4.07}, {"start": 290.63, "end": 308.11, "duration": 17.48}, {"start": 308.11, "end": 310.63, "duration": 2.52}, {"start": 310.63, "end": 329.92, "duration": 19.29}, {"start": 329.92, "end": 334.1, "duration": 4.18}, {"start": 334.1, "end": 342.83, "duration": 8.73}, {"start": 342.83, "end": 345.4, "duration": 2.57}, {"start": 345.51, "end": 353.86, "duration": 8.35}, {"start": 353.86, "end": 362.57, "duration": 8.71}, {"start": 362.57, "end": 368.3, "duration": 5.73}, {"start": 368.3, "end": 371.32, "duration": 3.02}, {"start": 371.32, "end": 388.2, "duration": 16.88}, {"start": 388.2, "end": 390.98, "duration": 2.78}, {"start": 390.98, "end": 395.41, "duration": 4.43}, {"start": 395.41, "end": 399.59, "duration": 4.18}, {"start": 399.59, "end": 412.05, "duration": 12.46}, {"start": 412.05, "end": 417.76, "duration": 5.71}, {"start": 417.76, "end": 421.0, "duration": 3.24}, {"start": 421.0, "end": 427.62, "duration": 6.62}]