[{"start": 0.0, "end": 58.71, "duration": 58.71}, {"start": 58.71, "end": 91.69, "duration": 32.98}, {"start": 91.69, "end": 96.3, "duration": 4.61}, {"start": 96.3, "end": 118.9, "duration": 22.6}, {"start": 118.9, "end": 146.44, "duration": 27.54}, {"start": 146.44, "end": 161.8, "duration": 15.36}, {"start": 161.8, "end": 172.83, "duration": 11.03}, {"start": 172.83, "end": 193.42, "duration": 20.59}, {"start": 193.42, "end": 215.35, "duration": 21.93}, {"start": 215.35, "end": 336.88, "duration": 121.53}, {"start": 336.88, "end": 414.18, "duration": 77.3}, {"start": 414.18, "end": 427.47, "duration": 13.29}, {"start": 427.47, "end": 460.78, "duration": 33.31}, {"start": 460.78, "end": 516.12, "duration": 55.34}, {"start": 516.12, "end": 560.01, "duration": 43.89}, {"start": 560.01, "end": 582.32, "duration": 22.31}, {"start": 582.32, "end": 654.62, "duration": 72.3}]