[{"start": 0.0, "end": 10.77, "duration": 10.77}, {"start": 10.77, "end": 13.43, "duration": 2.66}, {"start": 17.08, "end": 23.02, "duration": 5.94}, {"start": 23.02, "end": 28.0, "duration": 4.98}, {"start": 28.0, "end": 37.47, "duration": 9.47}, {"start": 37.47, "end": 42.43, "duration": 4.96}, {"start": 42.66, "end": 52.65, "duration": 9.99}, {"start": 52.65, "end": 62.98, "duration": 10.33}, {"start": 64.57, "end": 68.37, "duration": 3.8}, {"start": 68.37, "end": 71.97, "duration": 3.6}, {"start": 71.97, "end": 75.08, "duration": 3.11}, {"start": 75.29, "end": 86.67, "duration": 11.38}, {"start": 86.67, "end": 90.67, "duration": 4.0}, {"start": 90.67, "end": 95.98, "duration": 5.31}, {"start": 95.98, "end": 108.7, "duration": 12.72}, {"start": 108.7, "end": 112.46, "duration": 3.76}, {"start": 112.46, "end": 116.18, "duration": 3.72}, {"start": 116.18, "end": 122.12, "duration": 5.94}, {"start": 122.12, "end": 124.81, "duration": 2.69}, {"start": 124.81, "end": 129.35, "duration": 4.54}, {"start": 129.35, "end": 138.31, "duration": 8.96}, {"start": 138.31, "end": 150.44, "duration": 12.13}, {"start": 150.44, "end": 159.14, "duration": 8.7}, {"start": 161.52, "end": 164.23, "duration": 2.71}, {"start": 166.36, "end": 170.12, "duration": 3.76}, {"start": 170.81, "end": 177.21, "duration": 6.4}, {"start": 177.53, "end": 185.5, "duration": 7.97}, {"start": 187.73, "end": 196.46, "duration": 8.73}, {"start": 196.91, "end": 206.41, "duration": 9.5}, {"start": 206.41, "end": 212.07, "duration": 5.66}, {"start": 212.07, "end": 236.14, "duration": 24.07}, {"start": 236.14, "end": 248.94, "duration": 12.8}, {"start": 248.94, "end": 258.23, "duration": 9.29}, {"start": 258.23, "end": 266.77, "duration": 8.54}, {"start": 266.77, "end": 272.25, "duration": 5.48}, {"start": 272.25, "end": 279.95, "duration": 7.7}, {"start": 279.95, "end": 283.81, "duration": 3.86}, {"start": 285.13, "end": 288.41, "duration": 3.28}, {"start": 289.66, "end": 295.41, "duration": 5.75}, {"start": 295.41, "end": 302.33, "duration": 6.92}, {"start": 303.42, "end": 312.84, "duration": 9.42}, {"start": 312.84, "end": 316.61, "duration": 3.77}, {"start": 316.61, "end": 320.72, "duration": 4.11}, {"start": 320.72, "end": 328.69, "duration": 7.97}, {"start": 328.69, "end": 333.78, "duration": 5.09}, {"start": 333.78, "end": 340.55, "duration": 6.77}, {"start": 340.55, "end": 351.13, "duration": 10.58}, {"start": 351.86, "end": 365.17, "duration": 13.31}, {"start": 365.58, "end": 373.24, "duration": 7.66}, {"start": 374.75, "end": 378.4, "duration": 3.65}, {"start": 379.66, "end": 396.91, "duration": 17.25}, {"start": 397.05, "end": 403.91, "duration": 6.86}, {"start": 403.91, "end": 413.31, "duration": 9.4}, {"start": 413.31, "end": 436.35, "duration": 23.04}, {"start": 436.81, "end": 446.95, "duration": 10.14}, {"start": 449.39, "end": 461.35, "duration": 11.96}, {"start": 461.35, "end": 468.5, "duration": 7.15}, {"start": 468.5, "end": 476.53, "duration": 8.03}, {"start": 476.53, "end": 479.32, "duration": 2.79}, {"start": 479.32, "end": 484.97, "duration": 5.65}, {"start": 484.97, "end": 487.97, "duration": 3.0}, {"start": 487.97, "end": 501.2, "duration": 13.23}, {"start": 504.0, "end": 515.17, "duration": 11.17}, {"start": 515.17, "end": 523.65, "duration": 8.48}, {"start": 523.65, "end": 528.13, "duration": 4.48}, {"start": 528.13, "end": 537.46, "duration": 9.33}, {"start": 537.61, "end": 541.84, "duration": 4.23}, {"start": 544.32, "end": 547.66, "duration": 3.34}, {"start": 549.43, "end": 554.97, "duration": 5.54}, {"start": 555.36, "end": 561.94, "duration": 6.58}, {"start": 561.94, "end": 565.67, "duration": 3.73}, {"start": 565.67, "end": 578.58, "duration": 12.91}, {"start": 578.58, "end": 581.57, "duration": 2.99}, {"start": 581.6, "end": 590.06, "duration": 8.46}, {"start": 590.06, "end": 594.16, "duration": 4.1}, {"start": 594.16, "end": 596.83, "duration": 2.67}]