[{"start": 0.0, "end": 7.36, "duration": 7.36}, {"start": 7.36, "end": 13.02, "duration": 5.66}, {"start": 13.02, "end": 20.61, "duration": 7.59}, {"start": 20.61, "end": 26.57, "duration": 5.96}, {"start": 26.57, "end": 31.31, "duration": 4.74}, {"start": 37.12, "end": 45.55, "duration": 8.43}, {"start": 45.55, "end": 53.78, "duration": 8.23}, {"start": 53.78, "end": 68.14, "duration": 14.36}, {"start": 68.14, "end": 74.09, "duration": 5.95}, {"start": 74.09, "end": 79.54, "duration": 5.45}, {"start": 79.54, "end": 82.39, "duration": 2.85}, {"start": 83.32, "end": 94.53, "duration": 11.21}, {"start": 94.53, "end": 100.24, "duration": 5.71}, {"start": 100.24, "end": 116.12, "duration": 15.88}, {"start": 116.12, "end": 131.37, "duration": 15.25}, {"start": 131.37, "end": 137.78, "duration": 6.41}, {"start": 138.4, "end": 145.41, "duration": 7.01}, {"start": 145.41, "end": 175.42, "duration": 30.01}, {"start": 175.42, "end": 186.14, "duration": 10.72}, {"start": 186.8, "end": 199.42, "duration": 12.62}, {"start": 199.42, "end": 227.54, "duration": 28.12}, {"start": 228.46, "end": 239.09, "duration": 10.63}, {"start": 239.09, "end": 266.88, "duration": 27.79}, {"start": 266.88, "end": 273.64, "duration": 6.76}, {"start": 273.64, "end": 281.94, "duration": 8.3}]