[{"start": 1.16, "end": 7.33, "duration": 6.17}, {"start": 7.33, "end": 11.91, "duration": 4.58}, {"start": 12.13, "end": 15.12, "duration": 2.99}, {"start": 17.39, "end": 20.06, "duration": 2.67}, {"start": 20.06, "end": 25.95, "duration": 5.89}, {"start": 25.95, "end": 30.08, "duration": 4.13}, {"start": 30.08, "end": 33.78, "duration": 3.7}, {"start": 34.09, "end": 37.06, "duration": 2.97}, {"start": 37.06, "end": 39.8, "duration": 2.74}, {"start": 39.8, "end": 44.11, "duration": 4.31}, {"start": 44.11, "end": 48.29, "duration": 4.18}, {"start": 48.29, "end": 54.45, "duration": 6.16}, {"start": 54.45, "end": 58.17, "duration": 3.72}, {"start": 58.17, "end": 61.41, "duration": 3.24}, {"start": 61.41, "end": 64.42, "duration": 3.01}, {"start": 64.42, "end": 70.73, "duration": 6.31}, {"start": 70.73, "end": 73.51, "duration": 2.78}, {"start": 75.8, "end": 79.15, "duration": 3.35}, {"start": 79.15, "end": 85.11, "duration": 5.96}, {"start": 85.11, "end": 88.71, "duration": 3.6}, {"start": 88.71, "end": 93.08, "duration": 4.37}, {"start": 93.08, "end": 97.53, "duration": 4.45}, {"start": 97.8, "end": 101.84, "duration": 4.04}, {"start": 101.84, "end": 105.44, "duration": 3.6}, {"start": 105.44, "end": 108.62, "duration": 3.18}, {"start": 108.62, "end": 114.09, "duration": 5.47}, {"start": 114.09, "end": 118.84, "duration": 4.75}, {"start": 118.84, "end": 123.21, "duration": 4.37}, {"start": 123.21, "end": 127.85, "duration": 4.64}, {"start": 127.85, "end": 130.62, "duration": 2.77}, {"start": 133.1, "end": 139.33, "duration": 6.23}, {"start": 139.33, "end": 143.17, "duration": 3.84}, {"start": 143.17, "end": 147.5, "duration": 4.33}, {"start": 147.5, "end": 156.61, "duration": 9.11}, {"start": 156.61, "end": 160.23, "duration": 3.62}, {"start": 160.23, "end": 162.75, "duration": 2.52}, {"start": 162.75, "end": 167.13, "duration": 4.38}, {"start": 167.13, "end": 171.65, "duration": 4.52}, {"start": 171.65, "end": 175.34, "duration": 3.69}, {"start": 175.34, "end": 178.05, "duration": 2.71}, {"start": 178.05, "end": 183.26, "duration": 5.21}]