[{"start": 0.0, "end": 6.05, "duration": 6.05}, {"start": 6.05, "end": 13.95, "duration": 7.9}, {"start": 13.95, "end": 26.16, "duration": 12.21}, {"start": 26.16, "end": 30.78, "duration": 4.62}, {"start": 30.78, "end": 36.18, "duration": 5.4}, {"start": 36.18, "end": 39.21, "duration": 3.03}, {"start": 39.21, "end": 46.47, "duration": 7.26}, {"start": 46.47, "end": 50.84, "duration": 4.37}, {"start": 50.84, "end": 55.6, "duration": 4.76}, {"start": 55.6, "end": 64.93, "duration": 9.33}, {"start": 64.93, "end": 68.18, "duration": 3.25}, {"start": 68.18, "end": 79.95, "duration": 11.77}, {"start": 79.95, "end": 84.87, "duration": 4.92}, {"start": 84.87, "end": 93.53, "duration": 8.66}, {"start": 93.53, "end": 97.46, "duration": 3.93}, {"start": 97.46, "end": 112.56, "duration": 15.1}, {"start": 112.56, "end": 120.27, "duration": 7.71}, {"start": 120.27, "end": 128.0, "duration": 7.73}, {"start": 128.0, "end": 135.61, "duration": 7.61}, {"start": 135.61, "end": 140.42, "duration": 4.81}, {"start": 142.9, "end": 157.0, "duration": 14.1}, {"start": 157.0, "end": 163.69, "duration": 6.69}, {"start": 163.69, "end": 169.6, "duration": 5.91}, {"start": 169.6, "end": 174.97, "duration": 5.37}, {"start": 174.97, "end": 184.27, "duration": 9.3}, {"start": 184.27, "end": 197.36, "duration": 13.09}, {"start": 197.36, "end": 216.67, "duration": 19.31}, {"start": 216.67, "end": 233.55, "duration": 16.88}, {"start": 233.55, "end": 240.14, "duration": 6.59}, {"start": 240.14, "end": 259.72, "duration": 19.58}, {"start": 259.72, "end": 266.72, "duration": 7.0}, {"start": 266.72, "end": 271.44, "duration": 4.72}, {"start": 271.44, "end": 276.55, "duration": 5.11}, {"start": 276.55, "end": 280.67, "duration": 4.12}, {"start": 280.67, "end": 291.08, "duration": 10.41}, {"start": 291.08, "end": 295.9, "duration": 4.82}, {"start": 295.9, "end": 299.6, "duration": 3.7}, {"start": 299.6, "end": 319.57, "duration": 19.97}, {"start": 319.57, "end": 323.3, "duration": 3.73}, {"start": 325.79, "end": 330.43, "duration": 4.64}, {"start": 330.43, "end": 333.61, "duration": 3.18}, {"start": 333.61, "end": 336.4, "duration": 2.79}, {"start": 336.4, "end": 340.14, "duration": 3.74}, {"start": 340.14, "end": 343.74, "duration": 3.6}, {"start": 343.74, "end": 346.53, "duration": 2.79}, {"start": 346.53, "end": 371.18, "duration": 24.65}, {"start": 371.18, "end": 375.25, "duration": 4.07}, {"start": 375.25, "end": 384.53, "duration": 9.28}, {"start": 384.53, "end": 396.01, "duration": 11.48}, {"start": 396.01, "end": 401.56, "duration": 5.55}, {"start": 401.56, "end": 404.56, "duration": 3.0}, {"start": 404.56, "end": 416.41, "duration": 11.85}, {"start": 416.41, "end": 422.11, "duration": 5.7}, {"start": 422.11, "end": 425.59, "duration": 3.48}, {"start": 425.59, "end": 432.98, "duration": 7.39}, {"start": 432.98, "end": 445.8, "duration": 12.82}, {"start": 445.8, "end": 448.39, "duration": 2.59}, {"start": 448.39, "end": 452.07, "duration": 3.68}, {"start": 452.07, "end": 463.96, "duration": 11.89}, {"start": 463.96, "end": 480.45, "duration": 16.49}, {"start": 480.45, "end": 487.21, "duration": 6.76}, {"start": 487.21, "end": 490.34, "duration": 3.13}, {"start": 490.34, "end": 498.13, "duration": 7.79}, {"start": 498.13, "end": 501.93, "duration": 3.8}, {"start": 501.93, "end": 511.7, "duration": 9.77}, {"start": 511.7, "end": 515.32, "duration": 3.62}, {"start": 515.32, "end": 519.61, "duration": 4.29}, {"start": 519.61, "end": 523.33, "duration": 3.72}, {"start": 523.33, "end": 540.32, "duration": 16.99}, {"start": 540.32, "end": 548.63, "duration": 8.31}, {"start": 548.63, "end": 551.87, "duration": 3.24}, {"start": 551.87, "end": 559.52, "duration": 7.65}, {"start": 559.52, "end": 567.74, "duration": 8.22}, {"start": 567.74, "end": 570.82, "duration": 3.08}, {"start": 573.12, "end": 577.17, "duration": 4.05}, {"start": 577.17, "end": 580.21, "duration": 3.04}, {"start": 580.21, "end": 584.21, "duration": 4.0}, {"start": 584.21, "end": 589.49, "duration": 5.28}, {"start": 589.49, "end": 593.71, "duration": 4.22}, {"start": 593.71, "end": 596.63, "duration": 2.92}, {"start": 596.63, "end": 602.35, "duration": 5.72}, {"start": 604.75, "end": 609.47, "duration": 4.72}, {"start": 609.47, "end": 612.36, "duration": 2.89}]