[{"start": 5.36, "end": 9.79, "duration": 4.43}, {"start": 9.79, "end": 17.68, "duration": 7.89}, {"start": 20.06, "end": 24.46, "duration": 4.4}, {"start": 24.46, "end": 29.52, "duration": 5.06}, {"start": 29.52, "end": 32.7, "duration": 3.18}, {"start": 32.7, "end": 37.64, "duration": 4.94}, {"start": 37.64, "end": 45.47, "duration": 7.83}, {"start": 45.47, "end": 53.21, "duration": 7.74}, {"start": 53.21, "end": 59.11, "duration": 5.9}, {"start": 59.4, "end": 67.24, "duration": 7.84}, {"start": 67.24, "end": 70.93, "duration": 3.69}, {"start": 70.93, "end": 76.66, "duration": 5.73}, {"start": 80.45, "end": 85.67, "duration": 5.22}, {"start": 85.67, "end": 90.07, "duration": 4.4}, {"start": 90.7, "end": 93.7, "duration": 3.0}, {"start": 93.7, "end": 96.73, "duration": 3.03}, {"start": 99.02, "end": 103.34, "duration": 4.32}, {"start": 104.22, "end": 111.69, "duration": 7.47}, {"start": 111.69, "end": 117.36, "duration": 5.67}, {"start": 117.44, "end": 122.37, "duration": 4.93}, {"start": 122.37, "end": 128.38, "duration": 6.01}, {"start": 128.5, "end": 134.96, "duration": 6.46}, {"start": 134.96, "end": 138.1, "duration": 3.14}, {"start": 138.1, "end": 142.04, "duration": 3.94}, {"start": 142.04, "end": 147.4, "duration": 5.36}, {"start": 147.75, "end": 157.33, "duration": 9.58}, {"start": 157.33, "end": 161.74, "duration": 4.41}, {"start": 161.74, "end": 164.44, "duration": 2.7}]