[{"start": 0.0, "end": 3.67, "duration": 3.67}, {"start": 3.67, "end": 16.12, "duration": 12.45}, {"start": 23.0, "end": 65.36, "duration": 42.36}, {"start": 65.36, "end": 79.45, "duration": 14.09}, {"start": 79.45, "end": 85.93, "duration": 6.48}, {"start": 85.93, "end": 91.2, "duration": 5.27}, {"start": 91.2, "end": 127.93, "duration": 36.73}, {"start": 127.93, "end": 162.26, "duration": 34.33}, {"start": 162.26, "end": 175.3, "duration": 13.04}, {"start": 175.3, "end": 190.72, "duration": 15.42}, {"start": 190.72, "end": 194.77, "duration": 4.05}, {"start": 194.77, "end": 269.7, "duration": 74.93}, {"start": 269.7, "end": 303.87, "duration": 34.17}, {"start": 303.87, "end": 337.29, "duration": 33.42}, {"start": 337.29, "end": 340.15, "duration": 2.86}, {"start": 340.15, "end": 344.74, "duration": 4.59}]