[{"start": 0.53, "end": 3.9, "duration": 3.37}, {"start": 3.9, "end": 7.35, "duration": 3.45}, {"start": 7.35, "end": 10.03, "duration": 2.68}, {"start": 10.03, "end": 13.49, "duration": 3.46}, {"start": 13.49, "end": 16.38, "duration": 2.89}, {"start": 16.38, "end": 20.13, "duration": 3.75}, {"start": 22.24, "end": 25.09, "duration": 2.85}, {"start": 25.09, "end": 28.71, "duration": 3.62}, {"start": 28.71, "end": 32.09, "duration": 3.38}, {"start": 32.09, "end": 35.01, "duration": 2.92}, {"start": 35.01, "end": 37.99, "duration": 2.98}, {"start": 37.99, "end": 41.05, "duration": 3.06}, {"start": 41.05, "end": 44.41, "duration": 3.36}, {"start": 44.41, "end": 48.24, "duration": 3.83}, {"start": 48.93, "end": 52.37, "duration": 3.44}, {"start": 52.37, "end": 56.34, "duration": 3.97}, {"start": 56.34, "end": 59.61, "duration": 3.27}, {"start": 59.61, "end": 63.67, "duration": 4.06}, {"start": 63.9, "end": 67.5, "duration": 3.6}, {"start": 69.53, "end": 73.34, "duration": 3.81}, {"start": 73.34, "end": 78.0, "duration": 4.66}, {"start": 78.0, "end": 82.01, "duration": 4.01}, {"start": 82.01, "end": 85.84, "duration": 3.83}, {"start": 85.84, "end": 90.04, "duration": 4.2}, {"start": 90.04, "end": 92.78, "duration": 2.74}, {"start": 92.78, "end": 96.66, "duration": 3.88}, {"start": 96.66, "end": 99.72, "duration": 3.06}, {"start": 102.26, "end": 106.04, "duration": 3.78}, {"start": 106.04, "end": 110.75, "duration": 4.71}, {"start": 113.58, "end": 116.51, "duration": 2.93}, {"start": 118.87, "end": 123.34, "duration": 4.47}, {"start": 123.34, "end": 127.22, "duration": 3.88}, {"start": 129.49, "end": 132.39, "duration": 2.9}, {"start": 132.39, "end": 136.97, "duration": 4.58}, {"start": 136.97, "end": 140.61, "duration": 3.64}, {"start": 142.85, "end": 146.83, "duration": 3.98}, {"start": 146.83, "end": 151.33, "duration": 4.5}, {"start": 151.33, "end": 155.36, "duration": 4.03}, {"start": 155.36, "end": 159.15, "duration": 3.79}, {"start": 159.15, "end": 162.86, "duration": 3.71}, {"start": 162.86, "end": 166.34, "duration": 3.48}, {"start": 166.34, "end": 169.4, "duration": 3.06}, {"start": 169.4, "end": 171.92, "duration": 2.52}, {"start": 171.92, "end": 177.83, "duration": 5.91}, {"start": 177.83, "end": 181.39, "duration": 3.56}, {"start": 181.39, "end": 187.1, "duration": 5.71}, {"start": 187.1, "end": 191.45, "duration": 4.35}, {"start": 191.45, "end": 197.03, "duration": 5.58}, {"start": 197.03, "end": 200.23, "duration": 3.2}, {"start": 200.23, "end": 202.87, "duration": 2.64}, {"start": 203.04, "end": 207.42, "duration": 4.38}, {"start": 207.42, "end": 211.39, "duration": 3.97}]