[{"start": 0.0, "end": 13.9, "duration": 13.9}, {"start": 13.9, "end": 26.92, "duration": 13.02}, {"start": 33.56, "end": 49.4, "duration": 15.84}, {"start": 49.4, "end": 61.8, "duration": 12.4}, {"start": 61.8, "end": 72.25, "duration": 10.45}, {"start": 72.25, "end": 83.71, "duration": 11.46}, {"start": 83.71, "end": 99.77, "duration": 16.06}, {"start": 99.77, "end": 109.81, "duration": 10.04}, {"start": 109.81, "end": 120.98, "duration": 11.17}, {"start": 120.98, "end": 135.61, "duration": 14.63}, {"start": 135.61, "end": 144.47, "duration": 8.86}, {"start": 144.47, "end": 152.84, "duration": 8.37}, {"start": 152.84, "end": 161.01, "duration": 8.17}, {"start": 161.01, "end": 179.12, "duration": 18.11}, {"start": 179.12, "end": 182.71, "duration": 3.59}, {"start": 182.71, "end": 185.32, "duration": 2.61}, {"start": 185.32, "end": 194.76, "duration": 9.44}, {"start": 194.76, "end": 197.98, "duration": 3.22}, {"start": 197.98, "end": 206.86, "duration": 8.88}, {"start": 206.86, "end": 219.28, "duration": 12.42}, {"start": 219.28, "end": 228.36, "duration": 9.08}, {"start": 228.36, "end": 242.19, "duration": 13.83}, {"start": 242.19, "end": 245.58, "duration": 3.39}, {"start": 245.58, "end": 255.5, "duration": 9.92}, {"start": 255.5, "end": 273.55, "duration": 18.05}, {"start": 273.55, "end": 296.74, "duration": 23.19}, {"start": 296.74, "end": 299.92, "duration": 3.18}, {"start": 299.92, "end": 305.42, "duration": 5.5}, {"start": 305.42, "end": 310.14, "duration": 4.72}, {"start": 310.14, "end": 317.95, "duration": 7.81}, {"start": 317.95, "end": 343.7, "duration": 25.75}, {"start": 343.7, "end": 348.75, "duration": 5.05}, {"start": 348.75, "end": 358.81, "duration": 10.06}, {"start": 358.81, "end": 362.98, "duration": 4.17}, {"start": 362.98, "end": 371.45, "duration": 8.47}, {"start": 371.45, "end": 378.13, "duration": 6.68}, {"start": 378.13, "end": 393.28, "duration": 15.15}, {"start": 393.28, "end": 399.84, "duration": 6.56}, {"start": 399.84, "end": 415.95, "duration": 16.11}, {"start": 415.95, "end": 425.41, "duration": 9.46}, {"start": 425.41, "end": 436.3, "duration": 10.89}, {"start": 436.3, "end": 444.65, "duration": 8.35}, {"start": 444.65, "end": 448.82, "duration": 4.17}, {"start": 448.82, "end": 452.45, "duration": 3.63}, {"start": 452.45, "end": 462.93, "duration": 10.48}, {"start": 462.93, "end": 467.36, "duration": 4.43}, {"start": 467.36, "end": 492.76, "duration": 25.4}, {"start": 492.76, "end": 496.2, "duration": 3.44}, {"start": 496.2, "end": 507.5, "duration": 11.3}, {"start": 507.5, "end": 514.36, "duration": 6.86}, {"start": 514.36, "end": 518.28, "duration": 3.92}, {"start": 518.28, "end": 520.93, "duration": 2.65}]