[{"start": 0.0, "end": 6.15, "duration": 6.15}, {"start": 6.15, "end": 26.87, "duration": 20.72}, {"start": 26.87, "end": 43.21, "duration": 16.34}, {"start": 43.21, "end": 63.02, "duration": 19.81}, {"start": 63.02, "end": 83.16, "duration": 20.14}, {"start": 83.16, "end": 94.77, "duration": 11.61}, {"start": 94.77, "end": 100.34, "duration": 5.57}, {"start": 100.34, "end": 125.31, "duration": 24.97}, {"start": 125.31, "end": 137.68, "duration": 12.37}, {"start": 137.68, "end": 144.5, "duration": 6.82}, {"start": 144.5, "end": 148.73, "duration": 4.23}, {"start": 148.73, "end": 169.98, "duration": 21.25}, {"start": 169.98, "end": 173.91, "duration": 3.93}, {"start": 173.91, "end": 187.17, "duration": 13.26}, {"start": 187.17, "end": 199.32, "duration": 12.15}, {"start": 199.32, "end": 227.04, "duration": 27.72}, {"start": 227.04, "end": 240.3, "duration": 13.26}, {"start": 240.3, "end": 250.25, "duration": 9.95}, {"start": 250.25, "end": 269.22, "duration": 18.97}, {"start": 269.22, "end": 310.78, "duration": 41.56}, {"start": 310.78, "end": 326.53, "duration": 15.75}, {"start": 326.53, "end": 341.09, "duration": 14.56}, {"start": 341.09, "end": 351.29, "duration": 10.2}, {"start": 351.29, "end": 358.42, "duration": 7.13}, {"start": 358.42, "end": 362.81, "duration": 4.39}, {"start": 362.81, "end": 374.56, "duration": 11.75}, {"start": 374.56, "end": 378.76, "duration": 4.2}, {"start": 378.76, "end": 389.79, "duration": 11.03}, {"start": 389.79, "end": 396.19, "duration": 6.4}, {"start": 396.19, "end": 431.34, "duration": 35.15}, {"start": 431.34, "end": 435.26, "duration": 3.92}, {"start": 435.26, "end": 446.07, "duration": 10.81}, {"start": 446.07, "end": 459.46, "duration": 13.39}]